poetry_test_project_for_me/__init__.py
poetry_test_project_for_me/main.py
poetry_test_project_for_me-0.3.0.dist-info/METADATA
poetry_test_project_for_me-0.3.0.dist-info/WHEEL
poetry_test_project_for_me-0.3.0.dist-info/entry_points.txt
poetry_test_project_for_me-0.3.0.dist-info/RECORD
