Metadata-Version: 2.1
Name: poetry_test_project_for_me
Version: 0.3.0
Summary: A poetry python test projet
License: GPL-3.0-only
Keywords: poetry,testing_package
Author: Alex Brightwater
Author-email: alexander.brightwater@gmail.com
Requires-Python: ==3.11.*
Classifier: License :: OSI Approved :: GNU General Public License v3 (GPLv3)
Classifier: Operating System :: OS Independent
Classifier: Programming Language :: Python :: 3
Classifier: Programming Language :: Python :: 3.11
Requires-Dist: requests (>=2.32.3,<3.0.0)
